mmlmgn/ConstructHW.py
mmlmgn/DataProcess.py
mmlmgn/DataSet.py
mmlmgn/HypergraphConstructKNN.py
mmlmgn/HypergraphConstructKmeans.py
mmlmgn/Module.py
mmlmgn/__init__.py
mmlmgn/mmlmgn.py
mmlmgn/param.py
mmlmgn/trainer.py
mmlmgn/utils.py
mmlmgn-0.1.2.dist-info/LICENSE
mmlmgn-0.1.2.dist-info/METADATA
mmlmgn-0.1.2.dist-info/WHEEL
mmlmgn-0.1.2.dist-info/top_level.txt
mmlmgn-0.1.2.dist-info/RECORD
